cftime/_cftime.cpython-38-x86_64-linux-gnu.so
cftime/_strptime.py
cftime/__init__.py
cftime-1.6.3.dist-info/RECORD
cftime-1.6.3.dist-info/top_level.txt
cftime-1.6.3.dist-info/LICENSE
cftime-1.6.3.dist-info/WHEEL
cftime-1.6.3.dist-info/METADATA
